pygount/__init__.py
pygount/analysis.py
pygount/command.py
pygount/common.py
pygount/git_storage.py
pygount/lexers.py
pygount/summary.py
pygount/write.py
pygount/xmldialect.py
pygount-3.1.0.dist-info/METADATA
pygount-3.1.0.dist-info/WHEEL
pygount-3.1.0.dist-info/entry_points.txt
pygount-3.1.0.dist-info/licenses/LICENSE.txt
pygount-3.1.0.dist-info/RECORD
