Metadata-Version: 2.4
Name: pygount
Version: 3.1.0
Summary: count source lines of code (SLOC) using pygments
Project-URL: Homepage, https://github.com/roskakori/pygount
Project-URL: Repository, https://github.com/roskakori/pygount.git
Project-URL: Documentation, https://pygount.readthedocs.io
Project-URL: Issue Tracker, https://github.com/roskakori/pygount/issues
Project-URL: Changes, https://pygount.readthedocs.io/en/latest/changes.html
Author-email: Thomas Aglassinger <roskakori@users.sourceforge.net>
License-Expression: BSD-3-Clause
License-File: LICENSE.txt
Keywords: SLOC,code analysis,count
Classifier: Development Status :: 5 - Production/Stable
Classifier: Environment :: Console
Classifier: Intended Audience :: Developers
Classifier: License :: OSI Approved :: BSD License
Classifier: Natural Language :: English
Classifier: Operating System :: OS Independent
Classifier: Programming Language :: Python :: 3 :: Only
Classifier: Programming Language :: Python :: 3.9
Classifier: Programming Language :: Python :: 3.10
Classifier: Programming Language :: Python :: 3.11
Classifier: Programming Language :: Python :: 3.12
Classifier: Programming Language :: Python :: 3.13
Classifier: Topic :: Software Development
Requires-Python: <4,>=3.9
Requires-Dist: chardet<6,>=5
Requires-Dist: gitpython~=3.1
Requires-Dist: pygments<3,>=2
Requires-Dist: rich>=9
